README.md
setup.py
expire_lock/__init__.py
expire_lock.egg-info/PKG-INFO
expire_lock.egg-info/SOURCES.txt
expire_lock.egg-info/dependency_links.txt
expire_lock.egg-info/top_level.txt